{ "skaters": [{
    "name": "Boy George",
    "age": 28,
    "location": "New Mexico",
    "sponsors": "Hooley, pencil skateboards, apple",
    "description": "Up and comming ripper with cool style",
    "id": "1"
    }, {
    "name": "Skyler Tyler",
    "age": 15,
    "location": "los angeles california",
    "sponsors": "Hooley, shoe, park",
    "description": "Young guy who can ride a skateboard",
    "id": "2"
      }, {
    "name": "Stoney Baloney",
    "age": 42,
    "location": "Northern California",
    "sponsors": "Hooley",
    "description": "Old guy who still rides a skateboard",
    "id": "3"
  }]
}
